contrib/delete_old.py
example/trubackup.json
systemd/trubackup.service
systemd/trubackup.timer
tests/README.md
tests/docker-compose.yml
tests/integration.sh
tests/populate.sh
tests/retention.py
tests/testenv.sh
tests/trubackup.json
trubackup/__init__.py
trubackup/backup.py
trubackup/cli.py
trubackup/config.py
trubackup/context.py
trubackup/info.py
trubackup/localfs.py
trubackup/mongo.py
trubackup/mysql.py
trubackup/options.py
trubackup/postgresql.py
trubackup/restore.py
trubackup/s3.py
trubackup/utils.py
trubackup/restic/backup.py
trubackup/restic/restore.py
trubackup/restic/snapshot.py
trubackup-5.0.0.dist-info/LICENSE
trubackup-5.0.0.dist-info/METADATA
trubackup-5.0.0.dist-info/WHEEL
trubackup-5.0.0.dist-info/entry_points.txt
trubackup-5.0.0.dist-info/top_level.txt
trubackup-5.0.0.dist-info/RECORD
