Metadata-Version: 2.1
Name: trubackup
Version: 5.0.0
Summary: Piping backup tool wrapped around restic
Author-email: Illia Shestakov <i.shestakov@abstract-technology.de>
License: Apache-2.0
Requires-Python: >=3.11
License-File: LICENSE
Requires-Dist: click
Requires-Dist: pydantic
Requires-Dist: s3ball >=0.1.1
